SqlForWebNerds/README.md
SqlForWebNerds/__init__.py
SqlForWebNerds/__main__.py
SqlForWebNerds/file.epub
SqlForWebNerds/index.html
SqlForWebNerds/css/__init__.py
SqlForWebNerds/css/annotations.css
SqlForWebNerds/css/main.css
SqlForWebNerds/css/normalize.css
SqlForWebNerds/css/popup.css
SqlForWebNerds/font/__init__.py
SqlForWebNerds/font/fontello.eot
SqlForWebNerds/font/fontello.svg
SqlForWebNerds/font/fontello.ttf
SqlForWebNerds/font/fontello.woff
SqlForWebNerds/img/__init__.py
SqlForWebNerds/img/annotator-glyph-sprite.png
SqlForWebNerds/img/annotator-icon-sprite.png
SqlForWebNerds/img/apple-touch-icon.png
SqlForWebNerds/img/cancelfullscreen.png
SqlForWebNerds/img/close.png
SqlForWebNerds/img/fullscreen.png
SqlForWebNerds/img/loader.gif
SqlForWebNerds/img/menu-icon.png
SqlForWebNerds/img/save.png
SqlForWebNerds/img/saved.png
SqlForWebNerds/img/settings-s.png
SqlForWebNerds/img/settings.png
SqlForWebNerds/img/star.png
SqlForWebNerds/js/__init__.py
SqlForWebNerds/js/epub.js
SqlForWebNerds/js/epub.min.js
SqlForWebNerds/js/epub.min.map
SqlForWebNerds/js/hooks.min.js
SqlForWebNerds/js/hooks.min.map
SqlForWebNerds/js/reader.js
SqlForWebNerds/js/reader.js.map
SqlForWebNerds/js/reader.min.js
SqlForWebNerds/js/reader.min.map
SqlForWebNerds/js/hooks/__init__.py
SqlForWebNerds/js/hooks/extensions/__init__.py
SqlForWebNerds/js/hooks/extensions/highlight.js
SqlForWebNerds/js/libs/__init__.py
SqlForWebNerds/js/libs/jquery.min.js
SqlForWebNerds/js/libs/localforage.min.js
SqlForWebNerds/js/libs/screenfull.js
SqlForWebNerds/js/libs/screenfull.min.js
SqlForWebNerds/js/libs/zip.min.js
SqlForWebNerds/js/plugins/__init__.py
SqlForWebNerds/js/plugins/hypothesis.js
SqlForWebNerds/js/plugins/search.js
sql_for_web_nerds-2024.3.2.0.dist-info/METADATA
sql_for_web_nerds-2024.3.2.0.dist-info/WHEEL
sql_for_web_nerds-2024.3.2.0.dist-info/entry_points.txt
sql_for_web_nerds-2024.3.2.0.dist-info/top_level.txt
sql_for_web_nerds-2024.3.2.0.dist-info/RECORD
